{"filename": "lib32-libarchive-3.8.0-1-x86_64.pkg.tar.zst", "name": "lib32-libarchive", "base": "lib32-libarchive", "version": "3.8.0-1", "desc": "Multi-format archive and compression library - 32bit", "csize": "390034", "isize": "922348", "sha256sum": "5e125d204f27d016048fed89dd86b092d1b68442c7360f6d8b83a07956e45f81", "pgpsig": "iHUEABYKAB0WIQQEKYl95fO9rFN6MGltQr3RFuAGjwUCaCxGyQAKCRBtQr3RFuAGj+XMAQDbqOOQftvtoBiNP8f+YsbplvuRew7ffYO/g9Nv5On9wwD+KNQXEHL3C43cdVYTi+6UFQxfwTVYwS/0PGiUDlRTDQw=", "url": "https://libarchive.org", "license": ["BSD-4-Clause-UC", "BSD-2-Clause", "Apache-2.0 OR CC0-1.0 OR OpenSSL"], "arch": "x86_64", "builddate": "1747732089", "packager": "Christian Hesse <eworm@archlinux.org>", "provides": ["libarchive.so=13-32"], "depends": ["libarchive=3.8.0", "lib32-acl", "lib32-bzip2", "lib32-glibc", "lib32-libxml2", "lib32-lz4", "lib32-openssl", "lib32-xz", "lib32-zlib", "lib32-zstd"], "makedepends": ["git"]}