{"filename": "arch-wiki-lite-20241101-1-any.pkg.tar.zst", "name": "arch-wiki-lite", "base": "arch-wiki-lite", "version": "20241101-1", "desc": "Arch Wiki without HTML. 1/9 as big, easily searched & viewable on console", "csize": "17197842", "isize": "17373587", "sha256sum": "693b798eee70ee8e75d41ed12bd73af557bd293582fcca8ba5abd153d2a3cc8b", "pgpsig": "iHUEABYKAB0WIQQQlBXmkgB2Ccp+v+QAHPSBC+jZEQUCZyT3RAAKCRAAHPSBC+jZEWeaAQDqugWR7nVzwNT1DsDy0qN+HCJh248WTXH9c31fPUKCjAD8DuKn2ceUvWyj5qUXtleVTkk1cnrPNGRPieTxG9XOOgE=", "url": "https://gitlab.archlinux.org/grawlinson/arch-wiki-lite", "license": ["GFDL-1.3-or-later", "GPL-2.0-or-later"], "arch": "any", "builddate": "1730475755", "packager": "Jakub Klinkovsk\u00fd <lahwaacz@archlinux.org>", "depends": ["bash", "gzip"], "optdepends": ["arch-wiki-docs: for wiki-search-html", "dialog: for interactive menu", "xdg-utils: for wiki-search-html"], "makedepends": ["git", "python", "arch-wiki-docs=20241101"]}