{"filename": "cosmic-bg-1:1.0.14-1-x86_64.pkg.tar.zst", "name": "cosmic-bg", "base": "cosmic-bg", "version": "1:1.0.14-1", "desc": "COSMIC session service which applies backgrounds to displays", "groups": "cosmic", "csize": "2314070", "isize": "9191718", "sha256sum": "55d47f7a170371c8df8ba84005d0316fa84a994dd4c0f65e32ab3b4f8026d2a4", "pgpsig": "iHUEABYKAB0WIQTS6V/sAVzx+RGqqww9TFAIu1yNKQUCahcYtgAKCRA9TFAIu1yNKXFaAQCUupUSQmjBVOgVqA5+bymUC/nx+7auBsfZt3YlybHOwQEA9ObD5f4S9cNNVfBoWd/sJB7qQbKNAESd5THn8wZB7wQ=", "url": "https://github.com/pop-os/cosmic-bg", "license": "MPL-2.0", "arch": "x86_64", "builddate": "1779898444", "packager": "Peter Jung <ptr1337@archlinux.org>", "depends": ["cosmic-icon-theme", "libgcc", "glibc", "libxkbcommon"], "makedepends": ["clang", "cargo", "git", "just", "lld", "nasm"]}