{"filename": "drkonqi-6.2.2-1-x86_64.pkg.tar.zst", "name": "drkonqi", "base": "drkonqi", "version": "6.2.2-1", "desc": "The KDE crash handler", "groups": "plasma", "csize": "653162", "isize": "3219910", "sha256sum": "e8471453e6b2090284eff40cd7289aeef2baf5d4ff75fa7712757857bcfe02c3", "pgpsig": "iHUEABYKAB0WIQSP5qfUzELIPJvMqOMtoqzD7OTc5gUCZxkR5AAKCRAtoqzD7OTc5pWqAP0S1nSNSzmBZMW2TVIS/QAY+r2k6twE6thcJDL/L388nAD+Ln3vDBayOM4QqjdyArWnxFWUa0BMsIiwPKb1A0KGCQM=", "url": "https://kde.org/plasma-desktop/", "license": "GPL-2.0-or-later", "arch": "x86_64", "builddate": "1729680318", "packager": "Tomaz Canabrava <tcanabrava@archlinux.org>", "depends": ["gcc-libs", "gdb", "glibc", "kcmutils", "kconfig", "kcoreaddons", "kcrash", "ki18n", "kidletime", "kio", "kirigami", "kitemmodels", "knotifications", "kservice", "kstatusnotifieritem", "kwallet", "kwidgetsaddons", "kwindowsystem", "polkit-qt6", "python", "python-psutil", "python-pygdbmi", "python-sentry_sdk", "qt6-base", "qt6-declarative", "syntax-highlighting", "systemd-libs"], "makedepends": ["extra-cmake-modules"]}