{"filename": "erlang-erl_interface-28.0-2-x86_64.pkg.tar.zst", "name": "erlang-erl_interface", "base": "erlang", "version": "28.0-2", "desc": "Low level interface to C", "csize": "189657", "isize": "1303570", "sha256sum": "a2662a828da207755a92a348b1a12584f7a89839106d0c07c714266e77bcbd88", "pgpsig": "iHUEABYKAB0WIQTrPXZP9dh+CBij4OXwXowSExrrXgUCaDsLdQAKCRDwXowSExrrXsS1APwJfjbORYv9NLXtrzf7B+KTSlYwp4idXq3FiJ0VOpLqfQD/RSn0ttfmVhIDjPWDBW3rqlBLJa+0/cTUK4RWJNhzqA0=", "url": "https://erlang.org/", "license": "Apache-2.0", "arch": "x86_64", "builddate": "1748695980", "packager": "Carl Smedstad <carsme@archlinux.org>", "conflicts": "erlang-nox", "depends": ["erlang-core", "glibc"], "makedepends": ["gcc-libs", "git", "glib2", "glibc", "glu", "java-environment", "libglvnd", "libxslt", "lksctp-tools", "mesa", "ncurses", "openssl", "perl", "unixodbc", "webkit2gtk-4.1", "wxwidgets-common", "wxwidgets-gtk3", "zlib"]}