{"filename": "gearmand-1.1.22-2-x86_64.pkg.tar.zst", "name": "gearmand", "base": "gearmand", "version": "1.1.22-2", "desc": "Distributed job queue server.", "csize": "372835", "isize": "866192", "sha256sum": "c09333ac49e13cceb3223c85fe99cb72255e6fa8d3215b49ac17c366e13a97ea", "pgpsig": "iHUEABYKAB0WIQQMrarPcPZMZU4TGzERZ1x0NCnd7wUCaPFIFAAKCRARZ1x0NCnd79XzAP91vO6C3h4UH5MDk7W3q7dZnFVFUAp6jjeZEBSABGdWXwEAw07lvuWxhsLRCIy/HWHYbEu3AhrwdaYWxI6+6xGSMQk=", "url": "http://gearman.org/", "license": "BSD-3-Clause", "arch": "x86_64", "builddate": "1760643010", "packager": "Massimiliano Torromeo <mtorromeo@archlinux.org>", "replaces": "gearman", "conflicts": "gearman", "provides": ["gearman=1.1.22"], "depends": ["libevent", "boost-libs", "mariadb-libs", "postgresql-libs", "sqlite", "hiredis"], "makedepends": ["boost", "gperf", "python-sphinx"]}