{"filename": "gnome-chess-47.0-1-x86_64.pkg.tar.zst", "name": "gnome-chess", "base": "gnome-chess", "version": "47.0-1", "desc": "Play the classic two-player boardgame of chess", "groups": "gnome-extra", "csize": "490017", "isize": "2613534", "sha256sum": "8d5f5130f1d34d1432b8357bd6ad0dc948c3f6c31e6e04dd9e4dd89d8196c051", "pgpsig": "iHUEABYKAB0WIQSDvIiJNRtd67toQW64rAhgDxCM3wUCZuPLzQAKCRC4rAhgDxCM34lMAQCUWxaQ9z2zY7WXep0UY3phSuTblHy1dKX4qrP38hnDUgD7BzzAnN0upjc2EyU4YtjMCuE46rjMCS0OeqVL8j+20gg=", "url": "https://wiki.gnome.org/Apps/Chess", "license": "GPL-3.0-or-later", "arch": "x86_64", "builddate": "1726204574", "packager": "Jan Alexander Steffens (heftig) <heftig@archlinux.org>", "depends": ["cairo", "dconf", "glib2", "glibc", "gtk4", "hicolor-icon-theme", "libadwaita", "librsvg", "pango"], "optdepends": "gnuchess: Play against computer", "makedepends": ["git", "gobject-introspection", "meson", "vala", "yelp-tools"]}