{"filename": "kidentitymanagement-25.08.0-1-x86_64.pkg.tar.zst", "name": "kidentitymanagement", "base": "kidentitymanagement", "version": "25.08.0-1", "desc": "Library to assist in handling user identities", "csize": "483467", "isize": "1619557", "sha256sum": "093617dcb32b6adb969611e5fa246b0f4ecd7062ed42764fd2160a8985829399", "pgpsig": "iHUEABYKAB0WIQSP5qfUzELIPJvMqOMtoqzD7OTc5gUCaJ/BnAAKCRAtoqzD7OTc5mCwAQDAX3+fnnKRAuurvB9vDLxR4uMhiLCv88iME+7LE6Y8bgEA5vtrLBSFnIlehAU5txo9Cn+m7GTL2G1YCUrvAyVroAM=", "url": "https://kontact.kde.org", "license": "LGPL-2.0-or-later", "arch": "x86_64", "builddate": "1755183882", "packager": "Tomaz Canabrava <tcanabrava@archlinux.org>", "depends": ["gcc-libs", "glibc", "kcodecs", "kcompletion", "kconfig", "kcoreaddons", "ki18n", "kio", "kpimtextedit", "ktextaddons", "kwidgetsaddons", "kxmlgui", "qt6-base"], "optdepends": ["qt6-declarative: QML bindings", "kirigami-addons: QML bindings"], "makedepends": ["doxygen", "extra-cmake-modules", "kirigami-addons", "qt6-doc", "qt6-tools"]}