{"filename": "kodi-tools-texturepacker-21.0-7-x86_64.pkg.tar.zst", "name": "kodi-tools-texturepacker", "base": "kodi", "version": "21.0-7", "desc": "Kodi Texturepacker tool", "csize": "37286", "isize": "76288", "sha256sum": "062735eb166e02b934a79eb33016be34372411c05420ea7f334b586d5679e0ea", "pgpsig": "iHUEABYKAB0WIQRTHs82RKRP6gtH283h488FOUSL/wUCZobhTQAKCRDh488FOUSL/6Q7AQDSN7e/M2NEH7YBf2cU4FchIgcB0KFIFP574kHu/yNWlwD/f38BDKGuvB1jH7kpcQECKaDBnu44r+PLIJ+h1psgcAM=", "url": "https://kodi.tv", "license": "GPL2", "arch": "x86_64", "builddate": "1720113598", "packager": "Ike Devolder <ike.devolder@archlinux.org>", "depends": ["libpng", "giflib", "libjpeg-turbo", "lzo"], "makedepends": ["afpfs-ng", "bluez-libs", "cmake", "curl", "dav1d", "doxygen", "git", "glew", "gperf", "hicolor-icon-theme", "java-runtime<21", "fmt", "libaacs", "libass", "libbluray", "libcdio", "libcec", "libgl", "mariadb-libs", "libmicrohttpd", "libmodplug", "libmpeg2", "libnfs", "libplist", "libpulse", "libva", "libva-vdpau-driver", "libxrandr", "libxslt", "lirc", "lzo", "mesa", "nasm", "pipewire", "python-pycryptodomex", "python-pillow", "python-pybluez", "python-simplejson", "shairplay", "smbclient", "sndio", "spdlog", "taglib", "tinyxml", "swig", "upower", "giflib", "rapidjson", "ghostscript", "meson", "gtest", "graphviz", "pcre", "tinyxml2", "libdisplay-info", "python-setuptools", "wayland-protocols", "waylandpp", "libxkbcommon", "libinput"]}