{"filename": "konsole-25.08.0-1-x86_64.pkg.tar.zst", "name": "konsole", "base": "konsole", "version": "25.08.0-1", "desc": "KDE terminal emulator", "groups": ["kde-utilities", "kde-applications"], "csize": "2218504", "isize": "9788243", "sha256sum": "2c1bdcb5f1f3a4951d71183f5d27db0c667439a56f5a685e9adc09f0f4195183", "pgpsig": "iHUEABYKAB0WIQSP5qfUzELIPJvMqOMtoqzD7OTc5gUCaJ/WpQAKCRAtoqzD7OTc5jJRAQCIalz/8XtHP/HeYlINM8VzHiFgkvTwHnVJ2B/44EfHTgEA9gITEDn6cE/oKaVag75gDFjG0kjsoDA8dS0UAQePmA4=", "url": "https://apps.kde.org/konsole/", "license": ["LGPL-2.0-or-later", "GPL-2.0-or-later"], "arch": "x86_64", "builddate": "1755199693", "packager": "Tomaz Canabrava <tcanabrava@archlinux.org>", "depends": ["glibc", "gcc-libs", "icu", "kbookmarks", "kcolorscheme", "kconfig", "kconfigwidgets", "kcoreaddons", "kcrash", "kdbusaddons", "kglobalaccel", "kguiaddons", "ki18n", "kiconthemes", "kio", "knewstuff", "knotifications", "knotifyconfig", "kparts", "kpty", "kservice", "ktextwidgets", "kwidgetsaddons", "kwindowsystem", "kxmlgui", "qt6-base", "qt6-multimedia", "sh"], "optdepends": "keditbookmarks: to manage bookmarks", "makedepends": ["extra-cmake-modules", "kdoctools"]}