{"filename": "libwpe-1.16.0-3-x86_64.pkg.tar.zst", "name": "libwpe", "base": "libwpe", "version": "1.16.0-3", "desc": "General-purpose library for WPE WebKit", "csize": "56146", "isize": "313798", "sha256sum": "567d166e282df6af93251846b925da189e37bdd0b386f6ae97a97efc7c65c5e5", "pgpsig": "iHUEABYKAB0WIQSDvIiJNRtd67toQW64rAhgDxCM3wUCZu333wAKCRC4rAhgDxCM38r2AQDlsqR6Dc9wsQdukJeXUK/aMlmsxP6U2n5QF5bfhETfXAEA07mcl4+lbJCMfRAjKEHjjs1Wkl5PiOfnUd9EOBAEAQs=", "url": "https://wpewebkit.org", "license": "BSD-2-Clause", "arch": "x86_64", "builddate": "1726871345", "packager": "Jan Alexander Steffens (heftig) <heftig@archlinux.org>", "provides": ["libwpe-1.0.so=1-64"], "depends": ["gcc-libs", "glibc", "libegl", "libxkbcommon"], "makedepends": ["clang", "git", "hotdoc", "llvm", "mesa", "meson"]}