{"filename": "mariadb-12.2.2-2-x86_64.pkg.tar.zst", "name": "mariadb", "base": "mariadb", "version": "12.2.2-2", "desc": "Fast SQL database server, derived from MySQL", "csize": "30463744", "isize": "206246728", "sha256sum": "d5d2a2f5d2e09957b22f6bebecd00ad41fce1c3d2eb8a7bbd6d036d087fb8db1", "pgpsig": "iHUEABYKAB0WIQQEKYl95fO9rFN6MGltQr3RFuAGjwUCaZSkvwAKCRBtQr3RFuAGjwWVAP936GEKrHdeyz3qaVPwBnSJVUiXVlXGJHRyPE0SgT2h9QD+LFa/VEHGJRDcUHLXHnrSf53VZbUoMCsuhY0g1+xY8gs=", "url": "https://mariadb.org/", "license": "GPL-2.0-only", "arch": "x86_64", "builddate": "1771348334", "packager": "Christian Hesse <eworm@archlinux.org>", "conflicts": "mysql", "provides": ["mariadb-server=12.2.2", "mysql"], "depends": ["mariadb-clients=12.2.2", "bzip2", "libbz2.so=1.0-64", "coreutils", "libxml2", "libxml2.so=16-64", "lz4", "liblz4.so=1-64", "systemd-libs", "libsystemd.so=0-64", "zstd", "libzstd.so=1-64"], "optdepends": ["curl: for ha_s3 plugin", "cracklib: for cracklib plugin", "galera: for MariaDB cluster with Galera WSREP", "judy: for Open Query GRAPH (OQGraph) computation engine", "perl-dbd-mariadb: for mariadb-hotcopy, mariadb-convert-table-format and mariadb-setpermission", "python-mysqlclient: for myrocks_hotbackup", "xz: lzma provider"], "makedepends": ["git", "boost", "bzip2", "cmake", "cracklib", "curl", "jemalloc", "judy", "krb5", "liburing", "libxcrypt", "libxml2", "lz4", "openssl", "pcre2", "systemd", "zlib", "zstd", "xz"]}