{"filename": "mattermost-desktop-6.2.0-1-x86_64.pkg.tar.zst", "name": "mattermost-desktop", "base": "mattermost-desktop", "version": "6.2.0-1", "desc": "Mattermost Desktop application", "csize": "3365559", "isize": "10929907", "sha256sum": "229cd59dbf1d587e920dc8b5d7137f08f52506a34d95725b0893b79dcafbb47f", "pgpsig": "iHUEABYKAB0WIQQMrarPcPZMZU4TGzERZ1x0NCnd7wUCagwVNQAKCRARZ1x0NCnd76NzAP98BtblYFIt0ylCt7XnBrhgWsBajnxpYU17O3E4Kc4osAEAzbaGZuhYkqCVnwr8Cub5hDt6P8c9HRgggSBglYJRyAo=", "url": "https://github.com/mattermost/desktop", "license": "Apache-2.0", "arch": "x86_64", "builddate": "1779176487", "packager": "Massimiliano Torromeo <mtorromeo@archlinux.org>", "depends": ["electron41", "libxcrypt-compat"], "makedepends": ["git", "jq", "python-setuptools", "moreutils", "nodejs-lts-jod", "node-gyp", "npm"]}