{"filename": "opencl-rusticl-mesa-1:24.0.8-1-x86_64.pkg.tar.zst", "name": "opencl-rusticl-mesa", "base": "mesa", "version": "1:24.0.8-1", "desc": "Open-source OpenCL drivers - RustICL variant", "csize": "6898324", "isize": "27339664", "sha256sum": "36ca55967029c2e65e345cd0adc92a36559f94bc3950f8a149a820266b6e9080", "pgpsig": "iHUEABYKAB0WIQSDvIiJNRtd67toQW64rAhgDxCM3wUCZk/ydwAKCRC4rAhgDxCM3yguAQD51nIo0xBg8kf8kk2dDjA4mJcySUYoWlEWv6EyrRbPnQD/fVl4YJa2eZ9DDCyul5s085UjHP+mqo1aotzABJ8h7As=", "url": "https://www.mesa3d.org/", "license": "MIT AND BSD-3-Clause AND SGI-B-2.0", "arch": "x86_64", "builddate": "1716514042", "packager": "Jan Alexander Steffens (heftig) <heftig@archlinux.org>", "replaces": "opencl-mesa<=23.1.4-1", "conflicts": "opencl-mesa", "provides": ["opencl-driver"], "depends": ["clang", "expat", "gcc-libs", "glibc", "libdrm", "libelf", "llvm-libs", "spirv-llvm-translator", "spirv-tools", "zlib", "zstd", "libclc"], "optdepends": "opencl-headers: headers necessary for OpenCL development", "makedepends": ["clang", "expat", "gcc-libs", "glibc", "libdrm", "libelf", "libglvnd", "libva", "libvdpau", "libx11", "libxcb", "libxext", "libxfixes", "libxml2", "libxrandr", "libxshmfence", "libxxf86vm", "llvm", "llvm-libs", "lm_sensors", "rust", "spirv-llvm-translator", "spirv-tools", "systemd-libs", "vulkan-icd-loader", "wayland", "xcb-util-keysyms", "zlib", "zstd", "clang", "cmake", "elfutils", "glslang", "libclc", "meson", "python-mako", "python-packaging", "python-ply", "rust-bindgen", "wayland-protocols", "xorgproto", "valgrind", "directx-headers", "libomxil-bellagio"]}