{"filename": "perl-image-exiftool-13.36-1-any.pkg.tar.zst", "name": "perl-image-exiftool", "base": "perl-image-exiftool", "version": "13.36-1", "desc": "Reader and rewriter of EXIF information that supports raw files", "csize": "4642889", "isize": "18324077", "sha256sum": "51ccdcf6deee769522534f5c3a771048b4a1d0618216eb360cdb3b9216d2b2e4", "pgpsig": "iHUEABYKAB0WIQRUwf0nM2HqUUojd5Pylr3lA2jGzgUCaMB+hwAKCRDylr3lA2jGzkaPAPwPT+h9tA6I1vtrOK4n9nO5ZBZxFTbQuEA7/pbMvdhSzgD/aeluZZyDfsTB9Hkf8R55XqwHy7QECR06a2ehCGjCggI=", "url": "https://exiftool.org/", "license": "Artistic-1.0-Perl OR GPL-3.0-or-later", "arch": "any", "builddate": "1757445713", "packager": "T.J. Townsend <blakkheim@archlinux.org>", "replaces": "perl-exiftool", "provides": ["exiftool", "perl-exiftool=13.36"], "depends": ["perl"], "optdepends": ["perl-io-compress-brotli: Support for brotli-compressed metadata", "perl-archive-zip: Support for zip files, including epub"], "makedepends": ["git"]}