{"filename": "python-pymysql-1.2.0-1-any.pkg.tar.zst", "name": "python-pymysql", "base": "python-pymysql", "version": "1.2.0-1", "desc": "Pure Python MySQL Client", "csize": "106785", "isize": "537769", "sha256sum": "e433c4b4a48424c3512154a1258482664d1530e2c9a2e3684fbd13b1eb10f2e1", "pgpsig": "iHUEABYKAB0WIQRizHP4hOUpV7L92IObeih9mi7GCAUCag5DkwAKCRCbeih9mi7GCNbrAQDw47mU12S5xZIVRYAszbHU/pDxIoICB/eYaCUjYM98ZgD+NPCiPvnCV11ONCeQTKAa2gPW2e5vb/iW7yAOrx8fIg4=", "url": "https://github.com/PyMySQL/PyMySQL/", "license": "MIT", "arch": "any", "builddate": "1779319663", "packager": "David Runge <dvzrv@archlinux.org>", "depends": ["python"], "optdepends": ["python-cryptography: for RSA cryptography", "mariadb: for using a local MariaDB instance", "python-pynacl: for ed25519 cryptography"], "makedepends": ["python-build", "python-installer", "python-setuptools", "python-wheel"]}