{"filename": "python-blosc2-3.9.1-1-x86_64.pkg.tar.zst", "name": "python-blosc2", "base": "python-blosc2", "version": "3.9.1-1", "desc": "Wrapper for the blosc2 compressor", "csize": "606342", "isize": "2996093", "sha256sum": "e6c35509486cd2896b2c69c448a3c1a3d9e44221250ccc4d83d9394c4724f06f", "pgpsig": "iHUEABYKAB0WIQTrPXZP9dh+CBij4OXwXowSExrrXgUCaOKqxQAKCRDwXowSExrrXmO/AQDpAEGbte5Y6PdthwAMI9g3F8JO5HjFx2Gt2oWJ9sE4SgEAzjDDedHjpMZ/ZzwBcE+mJiDabg+9dCgiOPnTfOUKRQk=", "url": "https://github.com/Blosc/python-blosc2", "license": "BSD-3-Clause", "arch": "x86_64", "builddate": "1759684818", "packager": "Carl Smedstad <carsme@archlinux.org>", "depends": ["blosc2", "glibc", "python", "python-msgpack", "python-ndindex", "python-numexpr", "python-numpy", "python-platformdirs", "python-py-cpuinfo", "python-requests"], "makedepends": ["cmake", "cython", "git", "ninja", "python-build", "python-installer", "python-scikit-build-core", "python-setuptools"], "checkdepends": ["python-psutil", "python-pytest", "python-pytorch"]}