{"filename": "python-aws-sam-translator-1.98.0-1-any.pkg.tar.zst", "name": "python-aws-sam-translator", "base": "python-aws-sam-translator", "version": "1.98.0-1", "desc": "AWS Serverless Application Model (AWS SAM) prescribes rules for expressing Serverless applications on AWS", "csize": "580221", "isize": "4165501", "sha256sum": "9e78b3433851393c5a2ef445287bcc59a0cba048eb3c7e39594ea914bf1cb709", "pgpsig": "iHUEABYKAB0WIQTrPXZP9dh+CBij4OXwXowSExrrXgUCaEa4YwAKCRDwXowSExrrXlLCAQCeaYDoOHUybJO1/VVv6dGwOuulK7TwNkqRPgVEwFdSTgEA7WYkEaNK/26pL6n4Fnz2iu1ddqAxroGxFslLx6otzAA=", "url": "https://github.com/aws/serverless-application-model", "license": "Apache-2.0", "arch": "any", "builddate": "1749464977", "packager": "Carl Smedstad <carsme@archlinux.org>", "depends": ["python", "python-boto3", "python-botocore", "python-jsonschema", "python-pydantic", "python-typing_extensions"], "makedepends": ["python-build", "python-installer", "python-setuptools", "python-wheel"], "checkdepends": ["python-parameterized", "python-pytest", "python-pytest-rerunfailures", "python-yaml"]}