{"filename": "radicale-3.5.4-1-any.pkg.tar.zst", "name": "radicale", "base": "radicale", "version": "3.5.4-1", "desc": "Simple calendar (CalDAV) and contact (CardDAV) server", "csize": "322330", "isize": "1763411", "sha256sum": "5ac5dbc057488b932dd2ce738b5801285497f26903102bb2bada6b45fabc3b32", "pgpsig": "iHUEABYKAB0WIQQQlBXmkgB2Ccp+v+QAHPSBC+jZEQUCaDMUZAAKCRAAHPSBC+jZEaeMAQDKa/Bu/Z51jUITurAc/D1YPrRTAMlwg4XulSW3L74+6gD/V8IO4t/HHwCkv9Cl1nWRhvbj4Iz0W6vkIfePLl3vnAQ=", "url": "https://radicale.org/", "license": "GPL-3.0-or-later", "arch": "any", "builddate": "1748177958", "packager": "Jakub Klinkovsk\u00fd <lahwaacz@archlinux.org>", "depends": ["python", "python-bcrypt", "python-defusedxml", "python-passlib", "python-pika", "python-vobject"], "optdepends": ["python-pam: for PAM authentication", "python-ldap3: for LDAP authentication", "python-requests: for OAuth2 authentication"], "makedepends": ["python-build", "python-installer", "python-setuptools", "python-wheel"], "checkdepends": ["python-pytest", "python-waitress"]}