{"filename": "skim-0.18.0-2-x86_64.pkg.tar.zst", "name": "skim", "base": "skim", "version": "0.18.0-2", "desc": "Fuzzy Finder in Rust!", "csize": "1352976", "isize": "4181092", "sha256sum": "815f946d690fbeb651a9d0ba5638cc9eba40e009b5e3a76e7043b32530b85b0c", "pgpsig": "iHUEABYKAB0WIQTnXNSBSnetlDx6taPglZ/qi1UFOQUCaFJ9ewAKCRDglZ/qi1UFOZnkAP96MepzYJ/bVPLHPiOdfgKlX/ee/wfJOBj+oIrbfvjb1gEA4ZLf8Jvtz/RHJudwbGP/4ZTRwgslg49XVxLueusbeQg=", "url": "https://github.com/lotabout/skim", "license": "MIT", "arch": "x86_64", "builddate": "1750236321", "packager": "George Rawlinson <grawlinson@archlinux.org>", "depends": ["ncurses"], "optdepends": ["fish: for resp. key bindings", "bash: for resp. completions and key bindings, and for sk-tmux script", "tmux: for sk-tmux script", "vim-plugin-runtime: for N/Vim plugin", "zsh: for resp. completions and key bindings"], "makedepends": ["git", "rust"]}