{"filename": "sqlfluff-3.3.0-1-any.pkg.tar.zst", "name": "sqlfluff", "base": "sqlfluff", "version": "3.3.0-1", "desc": "A dialect-flexible and configurable SQL linter", "csize": "1408298", "isize": "10024763", "sha256sum": "883521b2a203f3a9f53febd1a816737532a12909d43195fa06062420e80cc502", "pgpsig": "iHUEABYKAB0WIQTrPXZP9dh+CBij4OXwXowSExrrXgUCZ2JvcwAKCRDwXowSExrrXqNEAP4rQg+OzgMmRT+sNseEwskiW/+WJ8PwNirLbKZFAgS8SAEAxNNtDndR1ViASlI1xBJe+/DvT5uR8/s4v6PLc/GxhQM=", "url": "https://github.com/sqlfluff/sqlfluff", "license": "MIT", "arch": "any", "builddate": "1734503579", "packager": "Carl Smedstad <carsme@archlinux.org>", "depends": ["python", "python-chardet", "python-click", "python-colorama", "python-diff-cover", "python-jinja", "python-pathspec", "python-platformdirs", "python-pluggy", "python-pytest", "python-regex", "python-tblib", "python-toml", "python-tqdm", "python-yaml"], "makedepends": ["python-build", "python-installer", "python-setuptools", "python-wheel"], "checkdepends": ["python-hypothesis"]}