{"filename": "syslog-ng-geoip2-4.10.2-2-x86_64.pkg.tar.zst", "name": "syslog-ng-geoip2", "base": "syslog-ng", "version": "4.10.2-2", "desc": "Next-generation syslogd with advanced networking and filtering capabilities (GeoIP2 module)", "groups": "syslog-ng-modules", "csize": "16444", "isize": "47384", "sha256sum": "4ef0fb3f459b80a0b191c26fabcec55bd8aef04ac4e8284766fb406d7be185d8", "pgpsig": "iHUEABYKAB0WIQTrPXZP9dh+CBij4OXwXowSExrrXgUCaO7OlQAKCRDwXowSExrrXi2eAP9zaVb5ksXnVW1jZxFPj6uP0/F+FQew7HqivRdwhT5DfgEAkffAKlWCaJcQx5Z0ukblkmtiOQdBtGacXvF51YRv2Ao=", "url": "https://github.com/syslog-ng/syslog-ng", "license": ["LGPL-2.1-or-later", "GPL-2.0-or-later"], "arch": "x86_64", "builddate": "1760480252", "packager": "Carl Smedstad <carsme@archlinux.org>", "depends": ["glib2", "glibc", "libmaxminddb", "syslog-ng"], "makedepends": ["abseil-cpp", "autoconf-archive", "bash", "curl", "docbook-xsl", "gawk", "gcc-libs", "git", "glib2", "glibc", "grpc", "hiredis", "json-c", "libcap", "libdbi", "libesmtp", "libmaxminddb", "libnet", "librabbitmq-c", "librdkafka", "libxslt", "mongo-c-driver", "net-snmp", "openssl", "pcre2", "protobuf", "python", "python-boto3", "python-botocore", "python-cachetools", "python-certifi", "python-charset-normalizer", "python-dateutil", "python-google-auth", "python-idna", "python-kubernetes", "python-oauthlib", "python-ply", "python-pyasn1", "python-pyasn1-modules", "python-pyyaml", "python-requests", "python-requests-oauthlib", "python-rsa", "python-setuptools", "python-urllib3", "python-websocket-client", "systemd", "systemd-libs", "zlib"], "checkdepends": ["criterion", "gperf", "python-pytest", "python-pytest-mock"]}