{"filename": "tcl-brltty-6.9.1-3-x86_64.pkg.tar.zst", "name": "tcl-brltty", "base": "brltty", "version": "6.9.1-3", "desc": "Braille display driver for Linux/Unix - TCL integration", "csize": "21949", "isize": "55803", "sha256sum": "72623a8a0177a51bc69edd0723b5a2a951ceb238cff312ca0ebf624c8206b62e", "pgpsig": "iHUEABYKAB0WIQQgmjbUPOLofahh/FhTnf1IE1GC7wUCajmB4AAKCRBTnf1IE1GC78pLAQDfSzF9QHQwJw0qrLWrdDr52u5e8uBK6+hbV9altPrnRAD/azYaYs40Eec8iAmhOgWFSYbyb6X5OtjtYDBLui4ZZAk=", "url": "https://brltty.app", "license": "LGPL-2.1-or-later", "arch": "x86_64", "builddate": "1782147129", "packager": "Juergen Hoetzel <juergen@archlinux.org>", "depends": ["brltty=6.9.1", "glibc", "tcl"], "makedepends": ["alsa-lib", "at-spi2-atk", "at-spi2-core", "atk", "bluez-libs", "cython", "dbus", "dracut", "espeak-ng", "expat", "festival", "gcc-libs", "glibc", "glib2", "gpm", "icu", "java-environment", "libcap", "liblouis", "libspeechd", "libxaw", "ncurses", "ocaml-ctypes", "ocaml-findlib", "pcre2", "polkit", "python-setuptools", "speech-dispatcher", "strip-nondeterminism", "systemd-libs", "tcl"]}