{"filename": "thunderbird-i18n-cy-128.2.2-1-x86_64.pkg.tar.zst", "name": "thunderbird-i18n-cy", "base": "thunderbird", "version": "128.2.2-1", "desc": "Welsh language pack for Thunderbird", "csize": "677951", "isize": "749050", "sha256sum": "a6e257dfd36d7c63bff36c7051786f73a60845e631b75b886730f02b99c2946d", "pgpsig": "iHUEABYKAB0WIQQhkbiUMbrAqLlt6T0kR0DRfH/Q7AUCZu1HJgAKCRAkR0DRfH/Q7Pf9AQDqC9rK88/FzKW2R367wdnE4uhwKh0YcAPdENA/HH7oswEAr4bNgg+7UOQZ7sHs8Z72G9Z6X7fuoEspwOyCo8yOLA0=", "url": "https://www.thunderbird.net/", "license": ["GPL-2.0-only", "MPL-2.0", "LGPL-2.1-only"], "arch": "x86_64", "builddate": "1726823371", "packager": "Leonidas Spyropoulos <artafinde@archlinux.org>", "depends": ["thunderbird>=128.2.2"], "makedepends": ["unzip", "zip", "diffutils", "python", "nasm", "mesa", "libpulse", "libice", "libsm", "rust", "clang", "llvm", "cbindgen", "nodejs", "lld", "gawk", "perl", "findutils", "libotr", "wasi-compiler-rt", "wasi-libc", "wasi-libc++", "wasi-libc++abi"]}