{"filename": "thunderbird-i18n-ms-140.0.1-1-x86_64.pkg.tar.zst", "name": "thunderbird-i18n-ms", "base": "thunderbird", "version": "140.0.1-1", "desc": "Malay language pack for Thunderbird", "csize": "282500", "isize": "352189", "sha256sum": "5baa9822cbc422fbc8d4cb1ee1c7a2e5a6ae393e3de5529f5d4ff4f4a0c65267", "pgpsig": "iHUEABYKAB0WIQQhkbiUMbrAqLlt6T0kR0DRfH/Q7AUCaHD6DQAKCRAkR0DRfH/Q7CQhAP4hz3O8fHh04TGGFKN81XLPZdbHrTa8boF9/1543Io0fgD/afpuhALfC9C1mbuZbm5Y1ur2W5UHaIQdJusiRBVEVQ4=", "url": "https://www.thunderbird.net/", "license": ["GPL-2.0-only", "MPL-2.0", "LGPL-2.1-only"], "arch": "x86_64", "builddate": "1752232576", "packager": "Leonidas Spyropoulos <artafinde@archlinux.org>", "depends": ["thunderbird>=140.0.1"], "makedepends": ["unzip", "zip", "diffutils", "python", "nasm", "mesa", "libpulse", "libice", "libsm", "rust", "clang", "llvm", "cbindgen", "nodejs", "lld", "gawk", "perl", "findutils", "libotr", "wasi-compiler-rt", "wasi-libc", "wasi-libc++", "wasi-libc++abi"]}