{"filename": "ttf-firacode-nerd-3.2.1-2-any.pkg.tar.zst", "name": "ttf-firacode-nerd", "base": "nerd-fonts", "version": "3.2.1-2", "desc": "Patched font Fira (Fura) Code from nerd fonts library", "groups": "nerd-fonts", "csize": "2927182", "isize": "43487513", "sha256sum": "083cea10fed334e62b6c8b1048d6285157e5710140d9b911092bfc4c2e003558", "pgpsig": "iHUEABYKAB0WIQRUwf0nM2HqUUojd5Pylr3lA2jGzgUCZj02TAAKCRDylr3lA2jGzmPyAP9p2ZUlgB4ykc9+zHSmog9uIfc2v3zDXuS6kudYknAU0AD+JWaIQtYJIiewBDo75nD85/YBqlJTKXQStrAMHI8kbgc=", "url": "https://github.com/ryanoasis/nerd-fonts", "license": "OFL-1.1", "arch": "any", "builddate": "1715286657", "packager": "T.J. Townsend <blakkheim@archlinux.org>", "replaces": "nerd-fonts-fira-code", "conflicts": "nerd-fonts-fira-code", "provides": ["ttf-font-nerd"]}