{"filename": "vim-9.2.0010-1-x86_64.pkg.tar.zst", "name": "vim", "base": "vim", "version": "9.2.0010-1", "desc": "Vi Improved, a highly configurable, improved version of the vi text editor", "csize": "2483703", "isize": "5298520", "sha256sum": "4c6bb1565d1acbf81f3effa4502ca3ebad42130df9e28a0f74eeea60a36baf79", "pgpsig": "iHUEABYKAB0WIQRUwf0nM2HqUUojd5Pylr3lA2jGzgUCaZN3XwAKCRDylr3lA2jGzg5lAQCpmVk1WzcX8HqgG53RMDiE3ftwvTNkZ1OjWxqfxqDynwD+IJWITboOUk13TIcORsyM2gYV7R9xHegFvhDwu2r/ogI=", "url": "https://www.vim.org", "license": "custom:vim", "arch": "x86_64", "builddate": "1771271068", "packager": "T.J. Townsend <blakkheim@archlinux.org>", "replaces": "vim-minimal", "conflicts": ["vim-minimal", "gvim"], "provides": ["xxd", "vim-minimal", "vim-plugin-runtime"], "depends": ["vim-runtime=9.2.0010-1", "gpm", "acl", "glibc", "libgcrypt", "zlib"], "optdepends": ["ruby: Ruby language support", "python: Python language support", "lua: Lua language support", "perl: Perl language support", "tcl: Tcl language support"], "makedepends": ["gawk", "git", "glibc", "gpm", "gtk3", "libcanberra", "libgcrypt", "libxt", "lua", "perl", "python", "ruby", "tcl", "zlib"]}