{"filename": "virtualbox-host-modules-lts-7.1.12-5-x86_64.pkg.tar.zst", "name": "virtualbox-host-modules-lts", "base": "virtualbox-host-modules-lts", "version": "7.1.12-5", "desc": "Virtualbox host kernel modules for LTS Kernel", "csize": "391286", "isize": "447168", "sha256sum": "44d4a5a4ab004aa86ccd3f020b0bfc6b7176dc720d8ba7e5d0c966bb54216052", "pgpsig": "iHUEABYKAB0WIQQEKYl95fO9rFN6MGltQr3RFuAGjwUCaI0qVQAKCRBtQr3RFuAGj0JwAQDF+WFAS0v6bjvCAeqmfaefR6klhiHxdreSHC+bEnY/wAEAr9vUuQohakNF3Fa3h4CCDRZmuexnVXDJ+GK9l+F71AI=", "url": "https://virtualbox.org/", "license": "GPL", "arch": "x86_64", "builddate": "1754081761", "packager": "Christian Hesse <eworm@archlinux.org>", "provides": ["VIRTUALBOX-HOST-MODULES"], "depends": ["linux-lts"], "makedepends": ["linux-lts-headers", "virtualbox-host-dkms=7.1.12"]}