{"filename": "vivaldi-7.1.3570.54-1-x86_64.pkg.tar.zst", "name": "vivaldi", "base": "vivaldi", "version": "7.1.3570.54-1", "desc": "An advanced browser made with the power user in mind.", "csize": "131244579", "isize": "414217007", "sha256sum": "6c9039bd4cd1160b55d403a6deb681f519f4c4d7725142e2f29b34415c829f3f", "pgpsig": "iHUEABYKAB0WIQRTHs82RKRP6gtH283h488FOUSL/wUCZ7X+uAAKCRDh488FOUSL/5xtAP9HDx7KznU7Z8kq1SONKQwUItYVuCJH7Wk2wKV6OAXxFAD+JP1l9HTRq9PUlTzyGjp4kMN+Rrrt4NmdCqow6k5JNwY=", "url": "https://vivaldi.com", "license": "custom", "arch": "x86_64", "builddate": "1739980257", "packager": "Ike Devolder <ike.devolder@archlinux.org>", "depends": ["libcups", "nss", "alsa-lib", "libxss", "ttf-font", "desktop-file-utils", "shared-mime-info", "hicolor-icon-theme"], "optdepends": ["libnotify: native notifications", "org.freedesktop.secrets: better secret storage in gnome-keyring or kwallet", "vivaldi-ffmpeg-codecs: playback of proprietary video/audio", "gtk3: gtk3 integration", "qt5-base: qt5 integration", "qt6-base: qt6 integration"], "makedepends": ["w3m"]}