{"filename": "zlib-ng-compat-2.2.3-2-x86_64.pkg.tar.zst", "name": "zlib-ng-compat", "base": "zlib-ng", "version": "2.2.3-2", "desc": "zlib replacement with optimizations for next generation systems (zlib compat)", "csize": "104407", "isize": "274815", "sha256sum": "d571bf936a0c926164abf36da2b2f285a42d4a647b7f2d5413ad77124f9d57d9", "pgpsig": "iHUEABYKAB0WIQQhkbiUMbrAqLlt6T0kR0DRfH/Q7AUCZ59mkAAKCRAkR0DRfH/Q7NQJAP46xFiZGCqlifCYwAUM6nsefyNQASfzrB0XEI9k1t12RQEAxTrENILYRLtchkVk8RTtNjf9glJiaCdWL0zk5RRV0A0=", "url": "https://github.com/zlib-ng/zlib-ng", "license": "Zlib", "arch": "x86_64", "builddate": "1738499551", "packager": "Leonidas Spyropoulos <artafinde@archlinux.org>", "conflicts": "zlib", "provides": ["zlib", "libz.so=1-64"], "depends": ["glibc"], "makedepends": ["cmake", "ninja"]}