{"filename": "glib2-devel-2.86.2-1-x86_64.pkg.tar.zst", "name": "glib2-devel", "base": "glib2", "version": "2.86.2-1", "desc": "Low level core library - development tools", "csize": "162820", "isize": "1257829", "md5sum": "6374bf52c115e28ad9464808e761e515", "sha256sum": "bffae138fce44e6ba39cf68b69cc9b8f43c767a8f46eb761cb34283d4e9538fe", "pgpsig": "iHUEABYKAB0WIQSDvIiJNRtd67toQW64rAhgDxCM3wUCaRzM5QAKCRC4rAhgDxCM328GAQDJA7PV5WJXrAGKCHQIH2HICKJvNwI8WVQvadKSV/1qHAD/Sq1ZWDYinm2G5OQx3cBFqr26Uggu/RrTPVcoDQn8cAA=", "url": "https://gitlab.gnome.org/GNOME/glib", "license": "LGPL-2.1-or-later", "arch": "x86_64", "builddate": "1763494822", "packager": "Jan Alexander Steffens (heftig) <heftig@archlinux.org>", "depends": ["glib2", "glibc", "libelf", "python", "python-packaging"], "makedepends": ["dbus", "dconf", "gettext", "gi-docgen", "git", "gobject-introspection", "libelf", "meson", "python", "python-docutils", "python-packaging", "shared-mime-info", "util-linux"], "checkdepends": ["desktop-file-utils", "glib2"]}