{"filename": "accountsservice-22.08.8-3-x86_64.pkg.tar.zst", "name": "accountsservice", "base": "accountsservice", "version": "22.08.8-3", "desc": "D-Bus interface for user account query and manipulation", "csize": "164551", "isize": "999241", "md5sum": "ee9a5c7bb6b671fe211d1fbcd158d4be", "sha256sum": "61569ae10fb72b1295f980cfc77bfdf5bef98fcf7760643abfd1b84a23677fab", "pgpsig": "iIsEABYIADMWIQQGaHodnU+rCLUP2Ss7lKgOUKR3xwUCZA9Z3xUcaGVmdGlnQGFyY2hsaW51eC5vcmcACgkQO5SoDlCkd8eawwEAgkZEIP7FMbq9EprNNUsW0tgxywcTvLIiIhGdNZpd+z4A/jLo7By3ZQ9+dDxWjpIQviSqSX3EFB4pl1gLcuGmjAsO", "url": "https://gitlab.freedesktop.org/accountsservice/accountsservice", "license": "GPL3", "arch": "x86_64", "builddate": "1678727461", "packager": "Jan Alexander Steffens (heftig) <heftig@archlinux.org>", "provides": ["libaccountsservice.so=0-64"], "depends": ["glib2", "libxcrypt", "polkit", "shadow", "systemd", "libcrypt.so=2-64", "libglib-2.0.so=0-64", "libgobject-2.0.so=0-64", "libgio-2.0.so=0-64", "libsystemd.so=0-64"], "makedepends": ["docbook-xsl", "git", "gobject-introspection", "gtk-doc", "meson", "vala", "xmlto"], "checkdepends": ["python-dbusmock", "python-gobject"], "tokens": ["accountsservice", "accountsservice_x86_64", "accountsservice_unstable", "accountsservice_x86_64_unstable"]}