{"filename": "clapper-docs-0.6.1-3-x86_64.pkg.tar.zst", "name": "clapper-docs", "base": "clapper", "version": "0.6.1-3", "desc": "Modern and user-friendly media player. (documentation)", "csize": "1169567", "isize": "5775750", "md5sum": "c6c2a32a7debff06251e0ac25d9d25ac", "sha256sum": "d0b10c14f558f326b4ba6468052db5ed338b27c9e3adf55aba12678639ac8ea8", "pgpsig": "iHUEABYKAB0WIQRebUlEiVizhDAfHyJJjvJH80DB4AUCZwZtqwAKCRBJjvJH80DB4KbTAQCcNHRYVuJvlG8qnBUBHdQRpvANyaawsWK9LzbwuS6oAgD+NxWSy9uSij2J2lKxFPUNVffjuHSsFsA4XG/f7VFjygg=", "url": "https://rafostar.github.io/clapper", "license": "LGPL-2.1-or-later AND GPL-3.0-or-later", "arch": "x86_64", "builddate": "1728474173", "packager": "Fabian Bornschein <fabiscafe@archlinux.org>", "makedepends": ["dconf", "glib2", "glibc", "graphene", "gst-plugins-bad", "gst-plugins-base", "gst-plugins-base-libs", "gst-plugins-good", "gstreamer", "gtk4", "hicolor-icon-theme", "libadwaita", "libmicrodns", "libsoup3", "pango", "gi-docgen", "git", "glib2-devel", "gobject-introspection", "meson", "vala"]}