{"filename": "cosmic-comp-1.0.0.alpha.5.1-1-x86_64.pkg.tar.zst", "name": "cosmic-comp", "base": "cosmic-comp", "version": "1.0.0.alpha.5.1-1", "desc": "Compositor for the COSMIC desktop environment", "groups": "cosmic", "csize": "8106430", "isize": "29736711", "md5sum": "7941f69f913859272043d9a4028e499b", "sha256sum": "cc5c58c229691a166d372193e2728bf5b60ec4ed5b3f84e44cef0f43a3fb35f9", "pgpsig": "iHUEABYKAB0WIQTS6V/sAVzx+RGqqww9TFAIu1yNKQUCZ4fqRwAKCRA9TFAIu1yNKcqYAP9ENkrXoJ9gTctkhOOrVfIr18EjqWoM3x/FqalEDVZQKgD/feWPpsRWLsrijLYlygEP6rb+2dsjR3hFx9l2x2RBqg8=", "url": "https://github.com/pop-os/cosmic-comp", "license": "GPL-3.0-only", "arch": "x86_64", "builddate": "1736960425", "packager": "Peter Jung <ptr1337@archlinux.org>", "depends": ["fontconfig", "gcc-libs", "glibc", "libdisplay-info", "libseat.so=1-64", "libinput", "libxcb", "libxkbcommon", "mesa", "pixman", "systemd-libs", "wayland"], "makedepends": ["cargo", "git", "lld"]}