{"filename": "doomretro-5.1.3-1-x86_64.pkg.tar.zst", "name": "doomretro", "base": "doomretro", "version": "5.1.3-1", "desc": "The classic, refined DOOM source port", "csize": "3232551", "isize": "12172306", "md5sum": "681f0ecb180751ae5ff38b2a2b539022", "sha256sum": "b4ef595a76a3709cb543c4af7f38b2faae399d36ca8416a59cc1823193bfc669", "pgpsig": "iHUEABYKAB0WIQTnXNSBSnetlDx6taPglZ/qi1UFOQUCZZCs1wAKCRDglZ/qi1UFOV7TAP9x3ucvRR8s43SgPaNERP2D8QXp6sXDMc7Rzb/znm9BcQEAmKd3lkj/BitTGxf9rBpTfMSHuhOh4fNXXCQymhjhzQs=", "url": "http://doomretro.com", "license": "GPL3", "arch": "x86_64", "builddate": "1703980160", "packager": "George Rawlinson <grawlinson@archlinux.org>", "depends": ["glibc", "sdl2", "sdl2_image", "sdl2_mixer"], "optdepends": "timidity++: for music playback", "makedepends": ["git", "cmake"], "tokens": ["doomretro", "doomretro_x86_64", "doomretro_unstable", "doomretro_x86_64_unstable"]}