{"filename": "firefox-132.0-1-x86_64.pkg.tar.zst", "name": "firefox", "base": "firefox", "version": "132.0-1", "desc": "Fast, Private & Safe Web Browser", "csize": "74510447", "isize": "255354247", "md5sum": "750274723499de4171a97c1f4b19c8dc", "sha256sum": "e65944a7b3bc49519724a72324db72c7e8ad242416c606b92c9beba45c80ebc3", "pgpsig": "iHUEABYKAB0WIQSDvIiJNRtd67toQW64rAhgDxCM3wUCZyBHMwAKCRC4rAhgDxCM3wThAP9MgwcyrM1mRnOY3+5fK1fQqUzBWCnFVBWC5oiCdL1cbgD/VJpDZ+m4JDfLpo9FHawxsKavweyp/jG87Go+2aKEygo=", "url": "https://www.mozilla.org/firefox/", "license": "MPL-2.0", "arch": "x86_64", "builddate": "1730124458", "packager": "Jan Alexander Steffens (heftig) <heftig@archlinux.org>", "depends": ["alsa-lib", "at-spi2-core", "bash", "cairo", "dbus", "ffmpeg", "fontconfig", "freetype2", "gcc-libs", "gdk-pixbuf2", "glib2", "glibc", "gtk3", "hicolor-icon-theme", "libpulse", "libx11", "libxcb", "libxcomposite", "libxdamage", "libxext", "libxfixes", "libxrandr", "libxss", "libxt", "mime-types", "nspr", "nss", "pango", "ttf-font"], "optdepends": ["libnotify: Notification integration", "hunspell-en_US: Spell checking, American English", "networkmanager: Location detection via available WiFi networks", "speech-dispatcher: Text-to-Speech", "xdg-desktop-portal: Screensharing with Wayland"], "makedepends": ["cbindgen", "clang", "diffutils", "imake", "jack", "lld", "llvm", "mesa", "nasm", "nodejs", "python", "rust", "unzip", "wasi-compiler-rt", "wasi-libc", "wasi-libc++", "wasi-libc++abi", "xorg-server-xvfb", "yasm", "zip"]}