{"filename": "gi-docgen-2025.5-1-any.pkg.tar.zst", "name": "gi-docgen", "base": "gi-docgen", "version": "2025.5-1", "desc": "Documentation generator for GObject-based libraries", "csize": "1266794", "isize": "2856857", "md5sum": "6429ac216fb094ec71de6f787023c774", "sha256sum": "be639847cddffb854b240522bbed122ccadb27ad89be78c8d147bbcc1d19fb12", "pgpsig": "iHUEABYKAB0WIQSDvIiJNRtd67toQW64rAhgDxCM3wUCaOpi8QAKCRC4rAhgDxCM34pkAQCJCf9G3oKOaWvAotfhlS9iYOrHuBf3t6GgjcwIEfr06gD/Z6oCk1PByNaTRG2gN8D46Bw+jzMHXw3kh8luhS0VPwI=", "url": "https://gnome.pages.gitlab.gnome.org/gi-docgen/", "license": "Apache-2.0 OR GPL-3.0-or-later", "arch": "any", "builddate": "1760191191", "packager": "Jan Alexander Steffens (heftig) <heftig@archlinux.org>", "depends": ["python", "python-jinja", "python-magic", "python-markdown", "python-markupsafe", "python-packaging", "python-pygments", "python-typogrify"], "makedepends": ["git", "python-build", "python-installer", "python-setuptools", "python-wheel"]}