{"filename": "intellij-idea-community-edition-4:2024.1.4-1-x86_64.pkg.tar.zst", "name": "intellij-idea-community-edition", "base": "intellij-idea-community-edition", "version": "4:2024.1.4-1", "desc": "IDE for Java, Groovy and other programming languages with advanced refactoring features", "csize": "415184606", "isize": "1785088090", "md5sum": "97cabe6df86e91f259ad6abcbb7665ed", "sha256sum": "6e0dd17682f66387ae483e5afa52e3a923856169196e82ebf186d4852021d2b8", "pgpsig": "iHUEABYKAB0WIQQhkbiUMbrAqLlt6T0kR0DRfH/Q7AUCZndmyQAKCRAkR0DRfH/Q7N2NAQC2/OF7Q8eUusa7T5HT8eeh9MD9ExKZf/c2gKfMlyb6kwD/ef05E0Kx05fuiU50s4dlQXzHC/P6iDm04cLzANy0Qwk=", "url": "https://www.jetbrains.com/idea/", "license": "Apache", "arch": "x86_64", "builddate": "1719099433", "packager": "Leonidas Spyropoulos <artafinde@archlinux.org>", "depends": ["giflib", "java-environment-openjdk=17", "python", "sh", "ttf-font", "libdbusmenu-glib", "fontconfig", "hicolor-icon-theme"], "optdepends": "lldb: lldb frontend integration", "makedepends": ["ant", "git", "maven"]}