{"filename": "libblockdev-swap-3.3.0-1-x86_64.pkg.tar.zst", "name": "libblockdev-swap", "base": "libblockdev", "version": "3.3.0-1", "desc": "A library for manipulating block devices - swap device support", "csize": "8930", "isize": "20363", "md5sum": "70944b9b0640e84065650c2a655433e1", "sha256sum": "72ccf2d59581580d8ad023d76f4f78016c00111bd12ac1319ba4284b5ce554f5", "pgpsig": "iHUEABYKAB0WIQRizHP4hOUpV7L92IObeih9mi7GCAUCZ632ZwAKCRCbeih9mi7GCJuXAP46Gg7myC8b2RuKMYXz2282ZbnFPkjZRbv74HcmAY4fhQD8Cg8Jj9CxKIYJT+ZXnqe4izO5KJJncKP73e02qtYf7Qk=", "url": "https://github.com/storaged-project/libblockdev", "license": "LGPL-2.1-or-later", "arch": "x86_64", "builddate": "1739453823", "packager": "David Runge <dvzrv@archlinux.org>", "provides": ["libbd_swap.so=3-64"], "depends": ["gcc-libs", "glib2", "libglib-2.0.so=0-64", "glibc", "libblockdev=3.3.0", "libbd_utils.so=3-64", "util-linux-libs", "libblkid.so=1-64"], "makedepends": ["autoconf-archive", "btrfs-progs", "cryptsetup", "device-mapper", "dosfstools", "e2fsprogs", "exfatprogs", "gcc-libs", "glib2", "glibc", "gobject-introspection", "gtk-doc", "json-glib", "kmod", "keyutils", "libatasmart", "libbytesize", "libnvme", "libyaml", "lvm2", "mdadm", "ndctl", "nss", "parted", "python", "systemd-libs", "util-linux", "util-linux-libs", "volume_key"]}