{"filename": "meld-3.22.2-1-any.pkg.tar.zst", "name": "meld", "base": "meld", "version": "3.22.2-1", "desc": "Compare files, directories and working copies", "csize": "892548", "isize": "5355258", "md5sum": "a9411735bed91963789b8e35e68df06f", "sha256sum": "b68dc7e6d44c464d80b335f31c16c2fe30c5d03172d600c5b37f8654e2d12449", "pgpsig": "iHUEABYKAB0WIQSDvIiJNRtd67toQW64rAhgDxCM3wUCZgA/wwAKCRC4rAhgDxCM3xFCAP9KmCbK3bWI0AHixAJKWdP+mF9GjL8VCa4BXHGDuHh4zgD+K5Bip9jgKpDnk0dS58E5dZzfJ4yB4VmXsPVx1WWXGAU=", "url": "https://meldmerge.org/", "license": "GPL-2.0-or-later", "arch": "any", "builddate": "1711292151", "packager": "Jan Alexander Steffens (heftig) <heftig@archlinux.org>", "depends": ["dconf", "gsettings-desktop-schemas", "gtksourceview4", "python-cairo", "python-gobject"], "makedepends": ["git", "meson", "yelp-tools"], "checkdepends": ["appstream-glib"], "tokens": ["meld", "meld_x86_64", "meld_unstable", "meld_x86_64_unstable"]}