{"filename": "nm-cloud-setup-1.42.0-2-x86_64.pkg.tar.zst", "name": "nm-cloud-setup", "base": "networkmanager", "version": "1.42.0-2", "desc": "Automatically configure NetworkManager in cloud", "csize": "51670", "isize": "115249", "md5sum": "91bd59813c8057620dbe67a995bfbea2", "sha256sum": "b8295066db186a93e86007c8b78deaa74b7c1e0ab0c6fa37486feb708deaadfc", "pgpsig": "iIsEABYIADMWIQQGaHodnU+rCLUP2Ss7lKgOUKR3xwUCY/PeBxUcaGVmdGlnQGFyY2hsaW51eC5vcmcACgkQO5SoDlCkd8eTGgEAykvrugSz4qu7UY6sm7U4JXdhmfpuufSS6XR713JoHFsA/29/JlHFHtk7pGu4yaROmlPdaEKqWOr5EOLnX+gbL4IJ", "url": "https://networkmanager.dev/", "license": "GPL", "arch": "x86_64", "builddate": "1676921807", "packager": "Jan Alexander Steffens (heftig) <heftig@archlinux.org>", "depends": ["networkmanager"], "makedepends": ["audit", "bluez-libs", "curl", "dhclient", "dhcpcd", "dnsmasq", "git", "glib2-docs", "gobject-introspection", "gtk-doc", "iproute2", "iptables-nft", "iwd", "jansson", "libmm-glib", "libndp", "libnewt", "libpsl", "libteam", "meson", "modemmanager", "nftables", "nss", "openresolv", "pacrunner", "perl-yaml", "polkit", "ppp=2.4.9", "python-gobject", "systemd", "vala", "vala", "wpa_supplicant"], "checkdepends": ["libx11", "python-dbus"], "tokens": ["nm-cloud-setup", "nm-cloud-setup_x86_64", "nm-cloud-setup_unstable", "nm-cloud-setup_x86_64_unstable"]}