{"filename": "opensmtpd-7.5.0p0-1-x86_64.pkg.tar.zst", "name": "opensmtpd", "base": "opensmtpd", "version": "7.5.0p0-1", "desc": "Free implementation of the server-side SMTP protocol", "csize": "549345", "isize": "1526665", "md5sum": "36f864e0fc747b9f01ae0f1d5dbc4512", "sha256sum": "587af537cad0b2acb0e552f5e1455115a284572d39088a805258a0abec54eef1", "pgpsig": "iHUEABYKAB0WIQRUwf0nM2HqUUojd5Pylr3lA2jGzgUCZhadSAAKCRDylr3lA2jGzqfZAQDY6xhSkL7e4fyhomcPwL5uJff1vl6Xuc5dzTjgynBlcAEApL2q1BzZt4VouSlUgVUWIfztI0XHpw01rNcjDFcjKgQ=", "url": "https://www.opensmtpd.org", "license": "custom", "arch": "x86_64", "builddate": "1712757994", "packager": "T.J. Townsend <blakkheim@archlinux.org>", "conflicts": ["smtp-forwarder", "smtp-server"], "provides": ["smtp-server", "smtp-forwarder"], "depends": ["libevent", "libxcrypt", "openssl", "pam", "systemd", "zlib"], "optdepends": "opensmtpd-filter-rspamd: rspamd integration", "makedepends": ["signify"], "tokens": ["opensmtpd", "opensmtpd_x86_64", "opensmtpd_unstable", "opensmtpd_x86_64_unstable"]}