{"filename": "php-pgsql-8.5.1-2-x86_64.pkg.tar.zst", "name": "php-pgsql", "base": "php", "version": "8.5.1-2", "desc": "PostgreSQL modules for PHP", "csize": "76574", "isize": "233728", "md5sum": "d8a866173987f0805470c03fc65cc188", "sha256sum": "4eba59d2215aaaa997ae2b19940bf797ac6e7063bdedcda21c61f8538569ab82", "pgpsig": "iHUEABYKAB0WIQQEKYl95fO9rFN6MGltQr3RFuAGjwUCaVwxiwAKCRBtQr3RFuAGj3mBAP9l5pKjOV3t4RWuB8d6UaPcj6eELkVlGpJh0wZg4UFFTgD/W7JUbovEYvhHG4eEhvUjsAxuSe7idcU5QOLPBIrBUQY=", "url": "https://www.php.net/", "license": "PHP-3.01", "arch": "x86_64", "builddate": "1767649287", "packager": "Christian Hesse <eworm@archlinux.org>", "provides": ["php-pgsql-interpreter=8.5"], "depends": ["php", "postgresql-libs"], "makedepends": ["apache", "enchant", "gd", "gmp", "icu", "libsodium", "libxslt", "libzip", "net-snmp", "argon2", "postgresql-libs", "sqlite", "systemd", "tidy", "unixodbc", "curl", "libtool", "postfix", "freetds", "pcre2", "oniguruma", "libtiff"], "checkdepends": ["procps-ng"]}