{"filename": "php-xsl-8.4.10-1-x86_64.pkg.tar.zst", "name": "php-xsl", "base": "php", "version": "8.4.10-1", "desc": "xsl module for PHP", "csize": "14372", "isize": "34944", "md5sum": "66eb6694ac29053b61d505163c12ea3d", "sha256sum": "ceb74937cd70a9ec5e5b0ddbaa4cdec8fe82452d31e3a919743a7472c5f36058", "pgpsig": "iHUEABYKAB0WIQQ+gMoai4n2nLpX2Yp2pe+QVESaXAUCaGfNfAAKCRB2pe+QVESaXN21AQDGwYCA52fSk9n6pc6yCWruZQRR+4SaGdXTqkcbxp4zjAEA7BuysPIadwAZEY5OG44BvZMXVWHX6UsPPbJDKShnbgY=", "url": "https://www.php.net/", "license": "PHP-3.01", "arch": "x86_64", "builddate": "1751632904", "packager": "Pierre Schmitz <pierre@archlinux.org>", "provides": ["php-xsl-interpreter=8.4"], "depends": ["php", "libxslt"], "makedepends": ["apache", "enchant", "gd", "gmp", "icu", "libsodium", "libxslt", "libzip", "net-snmp", "argon2", "postgresql-libs", "sqlite", "systemd", "tidy", "unixodbc", "curl", "libtool", "postfix", "freetds", "pcre2", "oniguruma"], "checkdepends": ["procps-ng"]}