{"filename": "py3status-3.57-3-any.pkg.tar.zst", "name": "py3status", "base": "py3status", "version": "3.57-3", "desc": "An extensible i3status replacement/wrapper written in python", "csize": "649132", "isize": "4114316", "md5sum": "57003d82b807fb9d59f3e10a04ca2119", "sha256sum": "a2498f7b23736abbe06df0a73de115658693f2decd222ff7e0ad096f63a37b72", "pgpsig": "iHUEABYKAB0WIQRizHP4hOUpV7L92IObeih9mi7GCAUCZg2WJAAKCRCbeih9mi7GCNFwAQDM6v9ChtlR3UJ3L2RsOXFbuupfVnC4wc1Nx13EhxpAEQD/WyJlkNxJ86t6H0Is58pMFqo8zqzM+vXt40DlO95sKQ8=", "url": "https://ultrabug.github.io/py3status/", "license": "BSD-3-Clause", "arch": "any", "builddate": "1712166348", "packager": "David Runge <dvzrv@archlinux.org>", "depends": ["python", "python-setuptools", "glib2"], "optdepends": ["i3blocks: for i3blocks modules", "i3status: for i3status modules", "iw: for the wifi module", "python-mpris2: for the mpris module", "python-pyudev: for udev event monitoring", "python-pydbus: for modules that rely on D-Bus", "python-pytz: for the clock module", "python-tzlocal: for the clock module", "pacman-contrib: for the arch_updates module"], "makedepends": ["python-build", "python-installer", "python-wheel", "python-hatchling"], "checkdepends": ["python-pytest"], "tokens": ["py3status", "py3status_x86_64", "py3status_unstable", "py3status_x86_64_unstable"]}