{"filename": "python-pytorch-opt-cuda-2.9.0-5-x86_64.pkg.tar.zst", "name": "python-pytorch-opt-cuda", "base": "python-pytorch", "version": "2.9.0-5", "desc": "Tensors and Dynamic neural networks in Python with strong GPU acceleration (with CUDA and AVX2 CPU optimizations)", "csize": "678409210", "isize": "1239394730", "md5sum": "78552294e8b192f321066fc0ba723719", "sha256sum": "e2b91d02347f900477dfb2cd2f741e4403c31b5b4426d3e460c7094d508e659b", "pgpsig": "iHUEABYKAB0WIQQQlBXmkgB2Ccp+v+QAHPSBC+jZEQUCaQ2PowAKCRAAHPSBC+jZEfydAQCKAXcnnxZy9ecYoo5d/qREfqR72h9vGnzY8Su+MApzGwEAtANH8GGdDjR/181vza51D1r47ghqO7iDQqttpvt1QwQ=", "url": "https://pytorch.org", "license": "BSD-3-Clause-Modification", "arch": "x86_64", "builddate": "1762452705", "packager": "Jakub Klinkovsk\u00fd <lahwaacz@archlinux.org>", "conflicts": "python-pytorch", "provides": ["python-pytorch=2.9.0", "python-pytorch-cuda=2.9.0"], "depends": ["abseil-cpp", "eigen", "gcc-libs", "gflags", "glibc", "google-glog", "intel-oneapi-mkl", "libuv", "numactl", "openmp", "openmpi", "protobuf", "pybind11", "python", "python-filelock", "python-jinja", "python-networkx", "python-numpy", "python-sympy", "python-typing_extensions", "python-yaml", "qt6-base", "vulkan-icd-loader", "cuda", "nccl", "cudnn", "magma-cuda", "onednn"], "optdepends": "python-onnxscript: for the ONNX exporter", "makedepends": ["cmake", "cuda", "cudnn", "doxygen", "git", "hipblaslt", "magma-cuda", "magma-hip", "miopen-hip", "nccl", "ninja", "onednn", "pkgconfig", "python-aotriton", "python-build", "python-installer", "python-setuptools", "python-triton", "python-yaml", "rocm-hip-sdk", "rocm-toolchain", "roctracer", "shaderc", "vulkan-headers"]}