{"filename": "python-numba-cuda-0.29.0-1-x86_64.pkg.tar.zst", "name": "python-numba-cuda", "base": "python-numba-cuda", "version": "0.29.0-1", "desc": "The CUDA target for Numba", "csize": "2404236", "isize": "19731935", "md5sum": "c580e67a74330f488e33db398e5a97c6", "sha256sum": "6d20789b6b2e0f3720db6c9b418e8da79e70189ddc7cbc881788d3921d7c7fcb", "pgpsig": "iHUEABYKAB0WIQQQlBXmkgB2Ccp+v+QAHPSBC+jZEQUCabpErgAKCRAAHPSBC+jZEd2iAQC6NtKpCpLRbEx6smmK870hRRciieQlOQLVUSNnQvPTuwD+KMplSe+tIvYvWOpvyKnTt8K23z89fmOZ43H9vrrI/Qc=", "url": "https://github.com/NVIDIA/numba-cuda", "license": "BSD-2-Clause", "arch": "x86_64", "builddate": "1773814889", "packager": "Jakub Klinkovsk\u00fd <lahwaacz@archlinux.org>", "depends": ["glibc", "libgcc", "libstdc++", "python", "python-cuda-bindings", "python-cuda-core", "python-cuda-pathfinder", "python-llvmlite", "python-numba", "python-numpy", "python-packaging", "python-yaml"], "optdepends": ["python-pygments: syntax highlighting in code dumps", "python-colorama: colors in error messages"], "makedepends": ["python-build", "python-installer", "python-setuptools", "python-wheel"]}