{"filename": "rsync-3.4.1-1-x86_64.pkg.tar.zst", "name": "rsync", "base": "rsync", "version": "3.4.1-1", "desc": "A fast and versatile file copying tool for remote and local files", "csize": "347102", "isize": "624469", "md5sum": "028ca8b2377da61adb444322a04cb93f", "sha256sum": "6b5798b8de2562463246c8c2c10e955757120318161b67dfca8d75245c8c1a71", "pgpsig": "iHUEABYKAB0WIQRUwf0nM2HqUUojd5Pylr3lA2jGzgUCZ4gj+AAKCRDylr3lA2jGznwTAQCbk3rmOAkEaHwScfRR5RJ4f7hRz7zzdcmB4bP+lHJyHQEAn8sUIadEzk4KqHYFljqmVH+l+l8ZMpL9UxtZis7zcgM=", "url": "https://rsync.samba.org/", "license": "GPL3", "arch": "x86_64", "builddate": "1736975247", "packager": "T.J. Townsend <blakkheim@archlinux.org>", "depends": ["acl", "libacl.so=1-64", "lz4", "openssl", "popt", "xxhash", "libxxhash.so=0-64", "zlib", "zstd"], "optdepends": "python: for rrsync", "makedepends": ["git", "python-commonmark"]}