{"filename": "rsync-3.4.3-1-x86_64.pkg.tar.zst", "name": "rsync", "base": "rsync", "version": "3.4.3-1", "desc": "A fast and versatile file copying tool for remote and local files", "csize": "385973", "isize": "739538", "md5sum": "e963a872357e106b9686c16a091bc1cb", "sha256sum": "f2ad0dcc4d7022cb7f04c4da716be067b93a95fc246f2c0259cb2dbb880684e5", "pgpsig": "iHUEABYKAB0WIQRUwf0nM2HqUUojd5Pylr3lA2jGzgUCagz+SQAKCRDylr3lA2jGzu6ZAP0Tmp00aArm1ozcqXTLlWzLYdmPRwxCyABmoh81/0XkbAEAm6wo7vjyUwmwo9rV23hpJWY6O/wU2e+wDFfeQtAhaQs=", "url": "https://rsync.samba.org/", "license": "GPL-3.0-or-later", "arch": "x86_64", "builddate": "1779236332", "packager": "T.J. Townsend <blakkheim@archlinux.org>", "depends": ["acl", "libacl.so=1-64", "lz4", "openssl", "popt", "xxhash", "libxxhash.so=0-64", "zlib", "zstd"], "optdepends": "python: for rrsync", "makedepends": ["git", "python-commonmark"]}