{"filename": "mkosi-14-2-any.pkg.tar.zst", "name": "mkosi", "base": "mkosi", "version": "14-2", "desc": "Build Legacy-Free OS Images", "csize": "227274", "isize": "1021972", "md5sum": "61708726e58052f7471489fd8396f587", "sha256sum": "c87e52f3bcf58ec5d5f93bdf46f1f22fa9f98041d3156ea8ffa0f46549d43c4f", "pgpsig": "iHUEABYKAB0WIQSZH24/B2XPYpWIhYYTmwnaW/DTOAUCY1wu+gAKCRATmwnaW/DTOLDDAQDuru0jmigzjdGHoIX6P3v1NBEQTXWVrEhxjeEqG5hBhwEA4ExMmHrXTF4qCsknzYBlaQY88RZYbFLnF+nrnpg5DwE=", "url": "https://github.com/systemd/mkosi", "license": "LGPL2.1", "arch": "any", "builddate": "1666985673", "packager": "David Runge <dvzrv@archlinux.org>", "depends": ["arch-install-scripts", "python", "python-pexpect", "qemu-img"], "optdepends": ["debian-archive-keyring: build Debian images", "btrfs-progs: raw_btrfs and subvolume output formats", "debootstrap: build Debian or Ubuntu images", "cryptsetup: add dm-verity partitions", "dosfstools: build bootable images", "gnupg: sign images", "qemu: run bootable images using QEMU", "sbsigntools: sign EFI binaries for UEFI SecureBoot", "squashfs-tools: raw_squashfs output format", "tar: tar output format", "ubuntu-keyring: build Ubuntu images", "xz: compress images with xz", "zstd: compress images with zstd"], "makedepends": ["python-build", "python-installer", "python-setuptools", "python-wheel"], "checkdepends": ["python-pexpect", "python-pytest"], "tokens": ["mkosi", "mkosi_x86_64", "mkosi_unstable", "mkosi_x86_64_unstable"]}