{"filename": "redo-python-0.42.d-2-any.pkg.tar.zst", "name": "redo-python", "base": "redo-python", "version": "0.42.d-2", "desc": "An implementation of the redo build system in Python", "csize": "87176", "isize": "232550", "md5sum": "a6a05d176170c8aade5a3673c89494af", "sha256sum": "b5545eac3734ef1b09f110993714d5056fc34804015e4de04faae608fb3da90b", "pgpsig": "iHUEABYKAB0WIQTnXNSBSnetlDx6taPglZ/qi1UFOQUCYhnV7AAKCRDglZ/qi1UFOToFAQC8s/42PVCzJkffO15jIC5oMvz0BB/PWZua6Uvd1pscqwEA5zhWw8RvfqWgQUAShiRqoznNJB8KiK+yrit3o6wcEg8=", "url": "https://github.com/apenwarr/redo", "license": "GPL", "arch": "any", "builddate": "1645860086", "packager": "George Rawlinson <grawlinson@archlinux.org>", "conflicts": ["redo-c", "redo-sh", "redo-jdebp"], "provides": ["redo"], "depends": ["python"], "optdepends": "python-setproctitle: pretty output", "makedepends": ["git", "python-beautifulsoup4", "python-markdown"], "tokens": ["redo-python", "redo-python_x86_64", "redo-python_unstable", "redo-python_x86_64_unstable"]}