{"filename": "cosmic-osd-1:1.0.13-1-x86_64.pkg.tar.zst", "name": "cosmic-osd", "base": "cosmic-osd", "version": "1:1.0.13-1", "desc": "COSMIC On-Screen Display", "groups": "cosmic", "csize": "6077707", "isize": "21705224", "md5sum": "89cd577842b9a3bcf19dd148b252a900", "sha256sum": "beee8054b1a2b21eccdf68a79653960bb3a025eda865ed5a9791744d8a7ba7e0", "pgpsig": "iHUEABYKAB0WIQTS6V/sAVzx+RGqqww9TFAIu1yNKQUCagb8kQAKCRA9TFAIu1yNKZzPAQCGm2vRW3Ve57WEdvu4jvCf/yOWYjNVv5xWfuJYbxCW0QEA1a9KJgDphugZkTMvTgnM5eFsa3ztLgP7hsdMuYCr2wY=", "url": "https://github.com/pop-os/cosmic-osd", "license": "GPL-3.0-only", "arch": "x86_64", "builddate": "1778842621", "packager": "Peter Jung <ptr1337@archlinux.org>", "depends": ["libgcc", "glibc", "libinput", "libpipewire", "libpulse", "libxkbcommon", "sound-theme-freedesktop", "systemd-libs", "wayland"], "makedepends": ["cargo", "clang", "git", "just", "lld"]}