{"filename": "kcalc-25.08.0-1-x86_64.pkg.tar.zst", "name": "kcalc", "base": "kcalc", "version": "25.08.0-1", "desc": "Scientific Calculator", "groups": ["kde-utilities", "kde-applications"], "csize": "744594", "isize": "3066302", "md5sum": "4e86dd8013e29951bd95fb59f049e087", "sha256sum": "747e7d41ace5e61cc2d44dd4c9457767bd4e7507e4e9532679bcf34911664aa0", "pgpsig": "iHUEABYKAB0WIQSP5qfUzELIPJvMqOMtoqzD7OTc5gUCaJ/VtAAKCRAtoqzD7OTc5gV/AQCo0Dsc+1r8rM6XkYsapp0RzSlTwTmxtumEqmA8hWsiKAEAo+UB2bxH2lNu0GzfCknXTe2Thuq79b4O/rk4FZTEXg8=", "url": "https://apps.kde.org/kcalc/", "license": ["LGPL-2.0-or-later", "GPL-2.0-or-later"], "arch": "x86_64", "builddate": "1755199272", "packager": "Tomaz Canabrava <tcanabrava@archlinux.org>", "depends": ["gcc-libs", "glibc", "gmp", "kcolorscheme", "kconfig", "kconfigwidgets", "kcoreaddons", "kcrash", "kguiaddons", "ki18n", "knotifications", "kwidgetsaddons", "kxmlgui", "libmpc", "mpfr", "qt6-base"], "makedepends": ["extra-cmake-modules", "kdoctools"]}