{"filename": "kitty-0.33.1-4-x86_64.pkg.tar.zst", "name": "kitty", "base": "kitty", "version": "0.33.1-4", "desc": "A modern, hackable, featureful, OpenGL-based terminal emulator", "csize": "11949514", "isize": "43253903", "md5sum": "d56810aad60eda87a4453501c03c7279", "sha256sum": "04aa4ce84aa6cf6731e548a25c567f1220fb6b8a779d6c18312c96f5446c6d4c", "pgpsig": "iHUEABYKAB0WIQQE16IZsKvkwrYqXmVKK3WGMeH9kQUCZg2qogAKCRBKK3WGMeH9kYv+AP9Gp/1FcaHFfujDJttrZR2U9cSS/qTnqSARlzmHe2/dSgEAvaVZXQhksEmXld5877Adqg3piqgWfHFrpCGhTTLRlgk=", "url": "https://github.com/kovidgoyal/kitty", "license": "GPL3", "arch": "x86_64", "builddate": "1712171271", "packager": "Maxim Baz <maximbaz@archlinux.org>", "depends": ["python3", "freetype2", "fontconfig", "wayland", "libx11", "libxkbcommon-x11", "libxcursor", "libxi", "hicolor-icon-theme", "libgl", "dbus", "lcms2", "librsync", "xxhash", "kitty-terminfo", "kitty-shell-integration"], "optdepends": ["python-pygments: syntax highlighting in kitty +kitten diff", "imagemagick: viewing images with icat", "libcanberra: playing \"bell\" sound on terminal bell"], "makedepends": ["libxinerama", "libxrandr", "wayland-protocols", "go", "simde"]}