{"filename": "kubeadm-1.27.3-1-x86_64.pkg.tar.zst", "name": "kubeadm", "base": "kubernetes", "version": "1.27.3-1", "desc": "A tool for quickly installing Kubernetes and setting up a secure cluster", "groups": "kubernetes-tools", "csize": "15463894", "isize": "78947566", "md5sum": "e56c9ab0525b3efc0ea8c6b62d13eebd", "sha256sum": "1b09692c74e2a28a2673661a9060aca2bb1124ec7a2c479f5ac73574b7a7eb49", "pgpsig": "iHUEABYKAB0WIQSZH24/B2XPYpWIhYYTmwnaW/DTOAUCZIrL+QAKCRATmwnaW/DTOFjpAP9TeQhpBWIhxXXO88IuKvkBGNsNFFEvFpvLYdG2PMauBgD/XTDgWGMKXJQtrc4QxMO1LWTnfThOI88nxlhcnwwKxAM=", "url": "https://kubernetes.io/", "license": "Apache", "arch": "x86_64", "builddate": "1686816846", "packager": "David Runge <dvzrv@archlinux.org>", "depends": ["glibc", "crictl"], "makedepends": ["cni-plugins", "conntrack-tools", "ethtool", "git", "go", "go-md2man", "iptables-nft", "socat", "rsync"], "tokens": ["kubeadm", "kubeadm_x86_64", "kubeadm_stable", "kubeadm_x86_64_stable"]}