{"filename": "loupe-45.1-1-x86_64.pkg.tar.zst", "name": "loupe", "base": "loupe", "version": "45.1-1", "desc": "A simple image viewer for GNOME", "groups": "gnome", "csize": "2009399", "isize": "6618177", "md5sum": "569ab5b62689217d3dd08e6f0692330e", "sha256sum": "d68158419fd955f45b75ad11406da51e1e0a6014857257d3b65c09033feb9cc8", "pgpsig": "iHUEABYIAB0WIQRebUlEiVizhDAfHyJJjvJH80DB4AUCZVSeLgAKCRBJjvJH80DB4BW4AP4iHQGaQXUqVm/Z1gPalZ0UUyILK4xk/wnxDG3eUv24bAD+PxloAdHXQTdv9/EzmRVvQvtQzeBza7q6KHw5k74WTAE=", "url": "https://gitlab.gnome.org/GNOME/loupe", "license": "GPL", "arch": "x86_64", "builddate": "1700043138", "packager": "Fabian Bornschein <fabiscafe@archlinux.org>", "depends": ["cairo", "glib2", "glycin", "graphene", "gtk4", "hicolor-icon-theme", "lcms2", "libadwaita", "libgweather-4"], "makedepends": ["git", "itstool", "meson", "rust"], "tokens": ["loupe", "loupe_x86_64", "loupe_stable", "loupe_x86_64_stable"]}