{"filename": "milou-6.2.4-1-x86_64.pkg.tar.zst", "name": "milou", "base": "milou", "version": "6.2.4-1", "desc": "A dedicated search application built on top of Baloo", "groups": "plasma", "csize": "79475", "isize": "283185", "md5sum": "210b8b018460d573ebe0f31f2b39797c", "sha256sum": "967333a0e7392046ba3aa4d6c088e4e158cb5ea7fa77758fc091a536d7bb129e", "pgpsig": "iHUEABYKAB0WIQSP5qfUzELIPJvMqOMtoqzD7OTc5gUCZ0cRtgAKCRAtoqzD7OTc5hZ6AP9M/tbNaxwzKiuOsdgS0IUA0PhBAxynTRCI4FfM7N8HkgD/YognK72ng1dVncv9hftuzvyKBg2KKEF1Z0BtKRUmmQg=", "url": "https://kde.org/plasma-desktop/", "license": "LGPL-2.0-or-later", "arch": "x86_64", "builddate": "1732706104", "packager": "Tomaz Canabrava <tcanabrava@archlinux.org>", "depends": ["gcc-libs", "glibc", "kconfig", "kirigami", "krunner", "ksvg", "libplasma", "qt6-base", "qt6-declarative"], "makedepends": ["extra-cmake-modules", "kdoctools"]}