{"filename": "ocaml-num-1.4-8-x86_64.pkg.tar.zst", "name": "ocaml-num", "base": "ocaml-num", "version": "1.4-8", "desc": "Library for arbitrary-precision integer and rational arithmetic that used to be part of the OCaml core distribution", "csize": "427788", "isize": "1488689", "md5sum": "561b07a18efb39c532bfe7eaa9694085", "sha256sum": "85cab91bc602e62bcca1b4ec533c6a3df787257e98659377bee451a401a349a2", "pgpsig": "iHUEABYIAB0WIQTFpZWP13hfrZgvouxaRbBrgcq4dgUCZHEIBQAKCRBaRbBrgcq4dvgHAQCqEkCTpg39956kOqMeAxlhhWATp9cu3jfU5qcoqN18UwEAnOYrLAMjtfG13L3RMvvNtMVK8YDXNIGRU4QiGh8HmA0=", "url": "https://github.com/ocaml/num", "license": "LGPL2.1", "arch": "x86_64", "builddate": "1685129212", "packager": "Konstantin Gizdov <kgizdov@archlinux.org>", "depends": ["ocaml>=5.0.0"], "makedepends": ["ocaml-findlib"], "tokens": ["ocaml-num", "ocaml-num_x86_64", "ocaml-num_stable", "ocaml-num_x86_64_stable"]}