{"filename": "ocaml-logs-0.7.0-2-x86_64.pkg.tar.zst", "name": "ocaml-logs", "base": "ocaml-logs", "version": "0.7.0-2", "desc": "Logging infrastructure for OCaml", "csize": "150386", "isize": "459437", "md5sum": "10ff3489695e23cbd3fc3f2b723ecf19", "sha256sum": "962f545891c75e16514ee89ce685d35ee88713fb11805f4f0bdd7d1a0e6653bc", "pgpsig": "iHUEABYKAB0WIQQgmjbUPOLofahh/FhTnf1IE1GC7wUCZXQ6dAAKCRBTnf1IE1GC7yiCAQD1BQvvffj74n2+1c3MMBneD+GmCGgk7PNnhE9S4xfiswEAqO8G4UGo7DSp09Yd4A+TXGVh54la3lNDXvdY+4HIiAM=", "url": "https://erratique.ch/software/logs", "license": "ISC", "arch": "x86_64", "builddate": "1702112569", "packager": "Juergen Hoetzel <juergen@archlinux.org>", "depends": ["ocaml", "ocaml-fmt", "ocaml-cmdliner"], "makedepends": ["ocaml-findlib", "ocamlbuild", "ocaml-topkg", "opam"], "tokens": ["ocaml-logs", "ocaml-logs_x86_64", "ocaml-logs_stable", "ocaml-logs_x86_64_stable"]}