{"filename": "percona-server-clients-8.0.34_26-6-x86_64.pkg.tar.zst", "name": "percona-server-clients", "base": "percona-server", "version": "8.0.34_26-6", "desc": "Percona Server client tools", "csize": "3298166", "isize": "84419056", "md5sum": "6f86900b651b17f86eb772ad5f80e653", "sha256sum": "26179b98190a94e35b3b4c93d82fb8fe2d7b21f4c3ebe95de2c7fe2a7c6e8126", "pgpsig": "iHUEABYIAB0WIQQMrarPcPZMZU4TGzERZ1x0NCnd7wUCZUax/gAKCRARZ1x0NCnd7z15AP4z6LSGXzH/6//eo98zFvBNdjGHvT27O3eTT22rX4F7uQD/dN3fL+wVC+Xo+y2M6iX46ngalb/OJPvWortxW2S4UgY=", "url": "https://www.percona.com/software/mysql-database/percona-server", "license": "GPL", "arch": "x86_64", "builddate": "1699130152", "packager": "Massimiliano Torromeo <mtorromeo@archlinux.org>", "conflicts": "mysql-clients", "provides": ["mysql-clients=8.0.34_26", "mariadb-clients=8.0.34_26"], "depends": ["libperconaserverclient", "zlib", "zstd", "lz4", "openssl", "jemalloc", "readline"], "makedepends": ["cmake", "zlib", "lz4", "zstd", "libaio", "systemd-tools", "pam", "numactl", "jemalloc", "openssl", "rpcsvc-proto", "doxygen", "graphviz", "libevent", "protobuf", "libfido2"], "tokens": ["percona-server-clients", "percona-server-clients_x86_64", "percona-server-clients_stable", "percona-server-clients_x86_64_stable"]}