{"filename": "perl-dist-checkconflicts-0.11-10-any.pkg.tar.zst", "name": "perl-dist-checkconflicts", "base": "perl-dist-checkconflicts", "version": "0.11-10", "desc": "Declare version conflicts for your dist", "csize": "9280", "isize": "12661", "md5sum": "59abd3a073b193f4b5c563af8a58492b", "sha256sum": "eeae38280f5c70b1233280d304fcad481a2e3ab5f3c4870de726ca2eb95791d4", "pgpsig": "iHUEABYKAB0WIQRUwf0nM2HqUUojd5Pylr3lA2jGzgUCZpHxlgAKCRDylr3lA2jGzhZmAQD0YN2kIz5+RowqHYbvgJIEZVzobI3hjXUWsvNIh9h2TwD/aU4x3c1L/C6E4zBfflRyMBtmasFugV4EKmcetYv/QAs=", "url": "https://metacpan.org/release/Dist-CheckConflicts", "license": ["GPL", "PerlArtistic"], "arch": "any", "builddate": "1720840588", "packager": "T.J. Townsend <blakkheim@archlinux.org>", "depends": ["perl-list-moreutils", "perl-exporter"], "makedepends": ["perl-extutils-makemaker"], "checkdepends": ["perl-test-fatal", "perl-module-runtime"]}