{"filename": "rocm-llvm-2:7.2.0-1-x86_64.pkg.tar.zst", "name": "rocm-llvm", "base": "rocm-llvm", "version": "2:7.2.0-1", "desc": "Radeon Open Compute - LLVM toolchain (llvm, clang, lld)", "csize": "1003232893", "isize": "4739857766", "md5sum": "354d7e4071c62b85fb1b19cce7774bdb", "sha256sum": "6918fa6c19c1df3ef0e5098b047bb5df7b0944aa6227e7dc573021193d42e849", "pgpsig": "iHUEABYKAB0WIQQEzwzW9u6TrhiW9YQH0GNRylsxvgUCaXo6jQAKCRAH0GNRylsxvhSqAP4iVuY7I7SO92xFVOmspQXbbcvCWV+DJHUqEeqU+1yn6wD7BGc5oCfN+DpETdiFhgkjHhPTf8LqfNmo3FaHBVucowM=", "url": "https://rocm.docs.amd.com/en/latest/reference/rocmcc.html", "license": "Apache-2.0 WITH LLVM-exception", "arch": "x86_64", "builddate": "1769615847", "packager": "Torsten Ke\u00dfler <tpkessler@archlinux.org>", "depends": ["rocm-core", "perl", "gcc-libs", "zlib", "zstd", "libffi", "libedit", "ncurses", "libxml2"], "makedepends": ["git", "cmake", "python", "ninja", "rocm-core", "rocm-cmake", "perl", "gcc-libs", "zlib", "zstd", "libffi", "libedit", "ncurses", "libxml2", "patchelf"]}