{"filename": "thunderbird-i18n-ast-139.0.2-1-x86_64.pkg.tar.zst", "name": "thunderbird-i18n-ast", "base": "thunderbird", "version": "139.0.2-1", "desc": "Asturian language pack for Thunderbird", "csize": "270711", "isize": "342368", "md5sum": "a1368233d5f31c0fa4ba30f9dcb845cd", "sha256sum": "502300aad5fd7a87ea8e2f643fc50395435421adb01276a74d2b5868e00aeb47", "pgpsig": "iHUEABYKAB0WIQQhkbiUMbrAqLlt6T0kR0DRfH/Q7AUCaEk5mwAKCRAkR0DRfH/Q7E3tAQC8kkhyhVBOuvDQEw9y3uZi8u+w/N4ZDt4yOWis3BsqHgD/TPVtpE2xBy/mZRd1+RcAKau8GIaEvhDko97uYGchTQU=", "url": "https://www.thunderbird.net/", "license": ["GPL-2.0-only", "MPL-2.0", "LGPL-2.1-only"], "arch": "x86_64", "builddate": "1749626873", "packager": "Leonidas Spyropoulos <artafinde@archlinux.org>", "depends": ["thunderbird>=139.0.2"], "makedepends": ["unzip", "zip", "diffutils", "python", "nasm", "mesa", "libpulse", "libice", "libsm", "rust", "clang", "llvm", "cbindgen", "nodejs", "lld", "gawk", "perl", "findutils", "libotr", "wasi-compiler-rt", "wasi-libc", "wasi-libc++", "wasi-libc++abi"]}